analoguesplit/__init__.py
analoguesplit/analoguesplit.py
analoguesplit-0.1.4.dist-info/LICENSE
analoguesplit-0.1.4.dist-info/METADATA
analoguesplit-0.1.4.dist-info/WHEEL
analoguesplit-0.1.4.dist-info/RECORD
