Metadata-Version: 2.1
Name: analoguesplit
Version: 0.1.4
Summary: A Chemically Biased Parametric Data Splitting Method
License: MIT
Author: Manas Mahale
Author-email: manas.mahale@bcp.edu.in
Requires-Python: >=3.8,<4.0
Classifier: License :: OSI Approved :: MIT License
Classifier: Programming Language :: Python :: 3
Classifier: Programming Language :: Python :: 3.8
Classifier: Programming Language :: Python :: 3.9
Classifier: Programming Language :: Python :: 3.10
Classifier: Programming Language :: Python :: 3.11
Classifier: Programming Language :: Python :: 3.12
Requires-Dist: loguru (>=0.7.2,<0.8.0)
Requires-Dist: matplotlib (>=3.9.0,<4.0.0)
Requires-Dist: notebook (>=7.2.1,<8.0.0)
Requires-Dist: numpy (>=1.2.6,<2.0.0)
Requires-Dist: pandas (>=2.2.3,<3.0.0)
Requires-Dist: rdkit (>=2024.3.1,<2025.0.0)
Requires-Dist: scikit-learn (>=1.5.0,<2.0.0)
Requires-Dist: six (>=1.16.0,<2.0.0)
Requires-Dist: xgboost (>=2.1.0,<3.0.0)
